iguanaio/__init__.py
iguanaio/access.py
iguanaio/iguanaclient.py
iguanaio/api/__init__.py
iguanaio/api/loans.py
iguanaio/api/reservations.py
iguanaio/api/userinfo.py
iguanaio-0.0.1.dist-info/METADATA
iguanaio-0.0.1.dist-info/WHEEL
iguanaio-0.0.1.dist-info/top_level.txt
iguanaio-0.0.1.dist-info/RECORD
